MANIFEST.in
setup.py
wsman/__init__.py
wsman/test_cache.py
wsman/utils.py
wsman.egg-info/PKG-INFO
wsman.egg-info/SOURCES.txt
wsman.egg-info/dependency_links.txt
wsman.egg-info/top_level.txt
wsman/cache/__init__.py
wsman/cache/ordereddict.py
wsman/filter/__init__.py
wsman/format/__init__.py
wsman/format/command.py
wsman/loghandlers/HTMLHandler.py
wsman/loghandlers/__init__.py
wsman/loghandlers/templates/command.html
wsman/loghandlers/templates/preamble.html
wsman/loghandlers/templates/tail.html
wsman/mixin/__init__.py
wsman/mixin/dictionary.py
wsman/parsers/__init__.py
wsman/provider/__init__.py
wsman/provider/remote.py
wsman/provider/winrm.py
wsman/provider/wsman.py
wsman/provider/wsmancli.py
wsman/response/__init__.py
wsman/response/association.py
wsman/response/fault.py
wsman/response/instance.py
wsman/response/reference.py
wsman/transport/__init__.py
wsman/transport/dummy/__init__.py
wsman/transport/dummy/responses/winrm/array.txt
wsman/transport/dummy/responses/winrm/epr.txt
wsman/transport/dummy/responses/winrm/fault.txt
wsman/transport/dummy/responses/winrm/get.txt
wsman/transport/dummy/responses/winrm/id.txt
wsman/transport/dummy/responses/winrm/instance.txt
wsman/transport/dummy/responses/winrm/instances.txt
wsman/transport/dummy/responses/winrm/invoke.txt
wsman/transport/dummy/responses/winrm/invoke_resp.txt
wsman/transport/dummy/responses/winrm/invoke_result.txt
wsman/transport/dummy/responses/winrm/wsmanfault.txt
wsman/transport/dummy/responses/wsmancli/epr.txt
wsman/transport/dummy/responses/wsmancli/fault.txt
wsman/transport/dummy/responses/wsmancli/get.txt
wsman/transport/dummy/responses/wsmancli/id.txt
wsman/transport/dummy/responses/wsmancli/instance.txt
wsman/transport/dummy/responses/wsmancli/instances.txt
wsman/transport/dummy/responses/wsmancli/invoke.txt
wsman/transport/dummy/responses/wsmancli/invoke_resp.txt
wsman/transport/dummy/responses/wsmancli/invoke_result.txt
wsman/transport/dummy/responses/wsmancli/wsmanfault.txt
wsman/transport/process/__init__.py
wsman/transport/process/_subprocess.py