Metadata-Version: 1.0
Name: wsman
Version: 0.9.27
Summary: Web Services Management
Home-page: UNKNOWN
Author: Vijay Halaharvi, Joseph Tallieu
Author-email: Vijay_Halaharvi@dell.com, joseph_tallieu@dell.com
License: Dell Software License
Platform: UNKNOWN
